pynovel/__init__.py
pynovel/run.py
pynovel-0.0.1.dist-info/METADATA
pynovel-0.0.1.dist-info/WHEEL
pynovel-0.0.1.dist-info/licenses/LICENSE
pynovel-0.0.1.dist-info/RECORD
