Metadata-Version: 2.4
Name: PyNovel
Version: 0.0.1
Summary: PyNovel is a library for developing visual novels in Python.
Author: Joseph Evans
License-File: LICENSE
Keywords: Engine,Visual Novel
Classifier: License :: OSI Approved :: MIT License
Classifier: Operating System :: OS Independent
Classifier: Programming Language :: Python :: 3
Requires-Python: >=3.8
